ctdataset/__init__.py
ctdataset/__main__.py
ctdataset/functional.py
ctdataset/dataset/__init__.py
ctdataset/dataset/ctdataset.py
ctdataset-1.1.0.dist-info/METADATA
ctdataset-1.1.0.dist-info/WHEEL
ctdataset-1.1.0.dist-info/top_level.txt
ctdataset-1.1.0.dist-info/RECORD
